dcompressee/__init__.py
dcompressee-1.0.0.dist-info/LICENSE
dcompressee-1.0.0.dist-info/METADATA
dcompressee-1.0.0.dist-info/WHEEL
dcompressee-1.0.0.dist-info/RECORD
