Metadata-Version: 2.1
Name: dcompressee
Version: 1.0.0
Summary: A small library to return temporary decompressed files when one needs them.
License: MIT
Author: Anders Goncalves da Silva
Author-email: andersgs@gmail.com
Requires-Python: >=3.10,<4.0
Classifier: License :: OSI Approved :: MIT License
Classifier: Programming Language :: Python :: 3
Classifier: Programming Language :: Python :: 3.10
Classifier: Programming Language :: Python :: 3.11
Requires-Dist: lz4 (>=4.3.2,<5.0.0)
